zon/__init__.py
zon/__main__.py
zon/cli.py
zon/binary/__init__.py
zon/binary/constants.py
zon/binary/decoder.py
zon/binary/encoder.py
zon/core/adaptive.py
zon/core/analyzer.py
zon/core/constants.py
zon/core/decoder.py
zon/core/encoder.py
zon/core/exceptions.py
zon/core/stream.py
zon/core/types.py
zon/core/utils.py
zon/integrations/__init__.py
zon/integrations/ai_sdk.py
zon/integrations/langchain.py
zon/integrations/openai.py
zon/llm/llm_client.py
zon/llm/optimizer.py
zon/llm/splitter.py
zon/llm/token_counter.py
zon/schema/inference.py
zon/schema/schema.py
zon/tools/__init__.py
zon/tools/helpers.py
zon/tools/printer.py
zon/tools/validator.py
zon/versioning/__init__.py
zon/versioning/migration.py
zon/versioning/versioning.py
zon_format-1.2.0.dist-info/METADATA
zon_format-1.2.0.dist-info/WHEEL
zon_format-1.2.0.dist-info/entry_points.txt
zon_format-1.2.0.dist-info/top_level.txt
zon_format-1.2.0.dist-info/RECORD
