Metadata-Version: 2.4
Name: zon-format
Version: 1.2.0
Summary: Zero Overhead Notation v1.2.0 - Human-readable data format with 30%+ compression over JSON, now with adaptive encoding
Author-email: Roni Bhakta <ronibhakta1@gmail.com>
Maintainer-email: Roni Bhakta <ronibhakta1@gmail.com>
License: MIT
Project-URL: Homepage, https://zonformat.org
Project-URL: Documentation, https://github.com/ZON-Format/ZON/blob/main/README.md
Project-URL: Repository, https://github.com/ZON-Format/ZON
Project-URL: Issues, https://github.com/ZON-Format/ZON/issues
Keywords: zon,serialization,llm,compression,token-efficiency,data-format,json-alternative,toon,token-efficient
Classifier: Development Status :: 5 - Production/Stable
Classifier: Intended Audience :: Developers
Classifier: Topic :: Software Development :: Libraries :: Python Modules
Classifier: Topic :: Text Processing :: Markup
Classifier: Programming Language :: Python :: 3
Classifier: Programming Language :: Python :: 3.8
Classifier: Programming Language :: Python :: 3.9
Classifier: Programming Language :: Python :: 3.10
Classifier: Programming Language :: Python :: 3.11
Classifier: Programming Language :: Python :: 3.12
Classifier: Operating System :: OS Independent
Requires-Python: >=3.8
